Metadata-Version: 1.0
Name: pack2
Version: 0.0.1
Summary: a pip-installable package example
Home-page: UNKNOWN
Author: vinay279
Author-email: mudiraj.vinay.279@gmail.com
License: MIT
Keywords: example
Platform: UNKNOWN
